mfpkage/__init__.py
mfpkage/mfage.py
mfpkage/mfprton.py
mfpkage/mfprtse.py
mfpkage-0.0.1.dist-info/LICENSE
mfpkage-0.0.1.dist-info/METADATA
mfpkage-0.0.1.dist-info/WHEEL
mfpkage-0.0.1.dist-info/top_level.txt
mfpkage-0.0.1.dist-info/RECORD
