Metadata-Version: 2.1
Name: mfpkage
Version: 0.0.1
Summary: This is my first package, setup-py Li Yanghao
Home-page: https://github.com/pypa/sampleproject
Author: Yanghao Li
Author-email: pyn1ck@protonmail.com
License: UNKNOWN
Project-URL: Bug Tracker, https://github.com/pypa/sampleproject/issues
Platform: UNKNOWN
Classifier: Programming Language :: Python :: 3
Classifier: License :: OSI Approved :: MIT License
Classifier: Operating System :: OS Independent
Requires-Python: >=3.6
License-File: LICENSE
